{
    "types": {},
    "endpoints": [
        {
            "example_identifier": null,
            "id": {
                "path": "/foo1",
                "method": "POST",
                "identifier_override": "endpoint_simple.foowithoutendpointerror"
            },
            "snippet": {
                "type": "csharp",
                "client": "using SeedApi;\n\nvar client = new SeedApiClient();\nawait client.Simple.FoowithoutendpointerrorAsync(new FooRequest { Bar = \"bar\" });\n"
            }
        },
        {
            "example_identifier": null,
            "id": {
                "path": "/foo2",
                "method": "POST",
                "identifier_override": "endpoint_simple.foo"
            },
            "snippet": {
                "type": "csharp",
                "client": "using SeedApi;\n\nvar client = new SeedApiClient();\nawait client.Simple.FooAsync(new FooRequest { Bar = \"bar\" });\n"
            }
        },
        {
            "example_identifier": null,
            "id": {
                "path": "/foo3",
                "method": "POST",
                "identifier_override": "endpoint_simple.foowithexamples"
            },
            "snippet": {
                "type": "csharp",
                "client": "using SeedApi;\n\nvar client = new SeedApiClient();\nawait client.Simple.FoowithexamplesAsync(new FooRequest { Bar = \"bar\" });\n"
            }
        }
    ]
}