{
  "info": {
    "name": "File Upload",
    "schema": "https://schema.getpostman.com/json/collection/v2.1.0/collection.json",
    "description": null
  },
  "variable": [
    {
      "key": "baseUrl",
      "value": "",
      "type": "string"
    }
  ],
  "auth": null,
  "item": [
    {
      "_type": "container",
      "description": null,
      "name": "Service",
      "item": [
        {
          "_type": "endpoint",
          "name": "Just File",
          "request": {
            "description": null,
            "url": {
              "raw": "{{baseUrl}}/just-file",
              "host": [
                "{{baseUrl}}"
              ],
              "path": [
                "just-file"
              ],
              "query": [],
              "variable": []
            },
            "header": [
              {
                "type": "text",
                "key": "Content-Type",
                "value": "application/json"
              }
            ],
            "method": "POST",
            "auth": null,
            "body": {
              "mode": "raw",
              "raw": "{}",
              "options": {
                "raw": {
                  "language": "json"
                }
              }
            }
          },
          "response": [
            {
              "name": "Success",
              "status": "OK",
              "code": 200,
              "originalRequest": {
                "description": null,
                "url": {
                  "raw": "{{baseUrl}}/just-file",
                  "host": [
                    "{{baseUrl}}"
                  ],
                  "path": [
                    "just-file"
                  ],
                  "query": [],
                  "variable": []
                },
                "header": [
                  {
                    "type": "text",
                    "key": "Content-Type",
                    "value": "application/json"
                  }
                ],
                "method": "POST",
                "auth": null,
                "body": {
                  "mode": "raw",
                  "raw": "{}",
                  "options": {
                    "raw": {
                      "language": "json"
                    }
                  }
                }
              },
              "description": null,
              "body": "",
              "_postman_previewlanguage": "json"
            }
          ]
        },
        {
          "_type": "endpoint",
          "name": "Optional Args",
          "request": {
            "description": null,
            "url": {
              "raw": "{{baseUrl}}/optional-args",
              "host": [
                "{{baseUrl}}"
              ],
              "path": [
                "optional-args"
              ],
              "query": [],
              "variable": []
            },
            "header": [
              {
                "type": "text",
                "key": "Content-Type",
                "value": "application/json"
              }
            ],
            "method": "POST",
            "auth": null,
            "body": {
              "mode": "raw",
              "raw": "{}",
              "options": {
                "raw": {
                  "language": "json"
                }
              }
            }
          },
          "response": [
            {
              "name": "Success",
              "status": "OK",
              "code": 200,
              "originalRequest": {
                "description": null,
                "url": {
                  "raw": "{{baseUrl}}/optional-args",
                  "host": [
                    "{{baseUrl}}"
                  ],
                  "path": [
                    "optional-args"
                  ],
                  "query": [],
                  "variable": []
                },
                "header": [
                  {
                    "type": "text",
                    "key": "Content-Type",
                    "value": "application/json"
                  }
                ],
                "method": "POST",
                "auth": null,
                "body": {
                  "mode": "raw",
                  "raw": "{}",
                  "options": {
                    "raw": {
                      "language": "json"
                    }
                  }
                }
              },
              "description": null,
              "body": "\"Foo\"",
              "_postman_previewlanguage": "json"
            }
          ]
        },
        {
          "_type": "endpoint",
          "name": "Simple",
          "request": {
            "description": null,
            "url": {
              "raw": "{{baseUrl}}/snippet",
              "host": [
                "{{baseUrl}}"
              ],
              "path": [
                "snippet"
              ],
              "query": [],
              "variable": []
            },
            "header": [
              {
                "type": "text",
                "key": "Content-Type",
                "value": "application/json"
              }
            ],
            "method": "POST",
            "auth": null,
            "body": null
          },
          "response": [
            {
              "name": "Success",
              "status": "OK",
              "code": 200,
              "originalRequest": {
                "description": null,
                "url": {
                  "raw": "{{baseUrl}}/snippet",
                  "host": [
                    "{{baseUrl}}"
                  ],
                  "path": [
                    "snippet"
                  ],
                  "query": [],
                  "variable": []
                },
                "header": [
                  {
                    "type": "text",
                    "key": "Content-Type",
                    "value": "application/json"
                  }
                ],
                "method": "POST",
                "auth": null,
                "body": null
              },
              "description": null,
              "body": "",
              "_postman_previewlanguage": "json"
            }
          ]
        }
      ]
    }
  ]
}