{
    "types": {},
    "endpoints": [
        {
            "example_identifier": null,
            "id": {
                "path": "/snippet",
                "method": "POST",
                "identifier_override": "endpoint_service.simple"
            },
            "snippet": {
                "type": "csharp",
                "client": "using SeedFileDownload;\n\nvar client = new SeedFileDownload.SeedFileDownloadClient();\nawait client.Service.SimpleAsync();\n"
            }
        }
    ]
}