{
    "apiName": {
        "originalName": "api",
        "camelCase": {
            "unsafeName": "api",
            "safeName": "api"
        },
        "snakeCase": {
            "unsafeName": "api",
            "safeName": "api"
        },
        "screamingSnakeCase": {
            "unsafeName": "API",
            "safeName": "API"
        },
        "pascalCase": {
            "unsafeName": "Api",
            "safeName": "Api"
        }
    },
    "apiDisplayName": null,
    "apiDocs": null,
    "auth": {
        "requirement": "ALL",
        "schemes": [
            {
                "_type": "bearer",
                "token": {
                    "originalName": "token",
                    "camelCase": {
                        "unsafeName": "token",
                        "safeName": "token"
                    },
                    "snakeCase": {
                        "unsafeName": "token",
                        "safeName": "token"
                    },
                    "screamingSnakeCase": {
                        "unsafeName": "TOKEN",
                        "safeName": "TOKEN"
                    },
                    "pascalCase": {
                        "unsafeName": "Token",
                        "safeName": "Token"
                    }
                },
                "tokenEnvVar": null,
                "docs": null
            }
        ],
        "docs": null
    },
    "headers": [],
    "idempotencyHeaders": [],
    "types": {
        "type_svc:myEnum": {
            "name": {
                "name": {
                    "originalName": "myEnum",
                    "camelCase": {
                        "unsafeName": "myEnum",
                        "safeName": "myEnum"
                    },
                    "snakeCase": {
                        "unsafeName": "my_enum",
                        "safeName": "my_enum"
                    },
                    "screamingSnakeCase": {
                        "unsafeName": "MY_ENUM",
                        "safeName": "MY_ENUM"
                    },
                    "pascalCase": {
                        "unsafeName": "MyEnum",
                        "safeName": "MyEnum"
                    }
                },
                "fernFilepath": {
                    "allParts": [
                        {
                            "originalName": "svc",
                            "camelCase": {
                                "unsafeName": "svc",
                                "safeName": "svc"
                            },
                            "snakeCase": {
                                "unsafeName": "svc",
                                "safeName": "svc"
                            },
                            "screamingSnakeCase": {
                                "unsafeName": "SVC",
                                "safeName": "SVC"
                            },
                            "pascalCase": {
                                "unsafeName": "Svc",
                                "safeName": "Svc"
                            }
                        }
                    ],
                    "packagePath": [],
                    "file": {
                        "originalName": "svc",
                        "camelCase": {
                            "unsafeName": "svc",
                            "safeName": "svc"
                        },
                        "snakeCase": {
                            "unsafeName": "svc",
                            "safeName": "svc"
                        },
                        "screamingSnakeCase": {
                            "unsafeName": "SVC",
                            "safeName": "SVC"
                        },
                        "pascalCase": {
                            "unsafeName": "Svc",
                            "safeName": "Svc"
                        }
                    }
                },
                "typeId": "type_svc:myEnum"
            },
            "shape": {
                "_type": "enum",
                "values": [
                    {
                        "name": {
                            "name": {
                                "originalName": "one",
                                "camelCase": {
                                    "unsafeName": "one",
                                    "safeName": "one"
                                },
                                "snakeCase": {
                                    "unsafeName": "one",
                                    "safeName": "one"
                                },
                                "screamingSnakeCase": {
                                    "unsafeName": "ONE",
                                    "safeName": "ONE"
                                },
                                "pascalCase": {
                                    "unsafeName": "One",
                                    "safeName": "One"
                                }
                            },
                            "wireValue": "one"
                        },
                        "availability": null,
                        "docs": null
                    },
                    {
                        "name": {
                            "name": {
                                "originalName": "two",
                                "camelCase": {
                                    "unsafeName": "two",
                                    "safeName": "two"
                                },
                                "snakeCase": {
                                    "unsafeName": "two",
                                    "safeName": "two"
                                },
                                "screamingSnakeCase": {
                                    "unsafeName": "TWO",
                                    "safeName": "TWO"
                                },
                                "pascalCase": {
                                    "unsafeName": "Two",
                                    "safeName": "Two"
                                }
                            },
                            "wireValue": "two"
                        },
                        "availability": null,
                        "docs": null
                    },
                    {
                        "name": {
                            "name": {
                                "originalName": "three",
                                "camelCase": {
                                    "unsafeName": "three",
                                    "safeName": "three"
                                },
                                "snakeCase": {
                                    "unsafeName": "three",
                                    "safeName": "three"
                                },
                                "screamingSnakeCase": {
                                    "unsafeName": "THREE",
                                    "safeName": "THREE"
                                },
                                "pascalCase": {
                                    "unsafeName": "Three",
                                    "safeName": "Three"
                                }
                            },
                            "wireValue": "three"
                        },
                        "availability": null,
                        "docs": null
                    },
                    {
                        "name": {
                            "name": {
                                "originalName": "four",
                                "camelCase": {
                                    "unsafeName": "four",
                                    "safeName": "four"
                                },
                                "snakeCase": {
                                    "unsafeName": "four",
                                    "safeName": "four"
                                },
                                "screamingSnakeCase": {
                                    "unsafeName": "FOUR",
                                    "safeName": "FOUR"
                                },
                                "pascalCase": {
                                    "unsafeName": "Four",
                                    "safeName": "Four"
                                }
                            },
                            "wireValue": "four"
                        },
                        "availability": null,
                        "docs": null
                    }
                ]
            },
            "referencedTypes": [],
            "examples": [],
            "availability": null,
            "docs": null
        }
    },
    "errors": {},
    "services": {
        "service_svc": {
            "availability": null,
            "name": {
                "fernFilepath": {
                    "allParts": [
                        {
                            "originalName": "svc",
                            "camelCase": {
                                "unsafeName": "svc",
                                "safeName": "svc"
                            },
                            "snakeCase": {
                                "unsafeName": "svc",
                                "safeName": "svc"
                            },
                            "screamingSnakeCase": {
                                "unsafeName": "SVC",
                                "safeName": "SVC"
                            },
                            "pascalCase": {
                                "unsafeName": "Svc",
                                "safeName": "Svc"
                            }
                        }
                    ],
                    "packagePath": [],
                    "file": {
                        "originalName": "svc",
                        "camelCase": {
                            "unsafeName": "svc",
                            "safeName": "svc"
                        },
                        "snakeCase": {
                            "unsafeName": "svc",
                            "safeName": "svc"
                        },
                        "screamingSnakeCase": {
                            "unsafeName": "SVC",
                            "safeName": "SVC"
                        },
                        "pascalCase": {
                            "unsafeName": "Svc",
                            "safeName": "Svc"
                        }
                    }
                }
            },
            "displayName": null,
            "basePath": {
                "head": "/",
                "parts": []
            },
            "headers": [],
            "pathParameters": [],
            "endpoints": [
                {
                    "id": "endpoint_svc.test",
                    "name": {
                        "originalName": "test",
                        "camelCase": {
                            "unsafeName": "test",
                            "safeName": "test"
                        },
                        "snakeCase": {
                            "unsafeName": "test",
                            "safeName": "test"
                        },
                        "screamingSnakeCase": {
                            "unsafeName": "TEST",
                            "safeName": "TEST"
                        },
                        "pascalCase": {
                            "unsafeName": "Test",
                            "safeName": "Test"
                        }
                    },
                    "displayName": null,
                    "auth": false,
                    "idempotent": false,
                    "baseUrl": null,
                    "method": "GET",
                    "path": {
                        "head": "/test",
                        "parts": []
                    },
                    "fullPath": {
                        "head": "/test",
                        "parts": []
                    },
                    "pathParameters": [],
                    "allPathParameters": [],
                    "queryParameters": [
                        {
                            "name": {
                                "name": {
                                    "originalName": "some-enum",
                                    "camelCase": {
                                        "unsafeName": "someEnum",
                                        "safeName": "someEnum"
                                    },
                                    "snakeCase": {
                                        "unsafeName": "some_enum",
                                        "safeName": "some_enum"
                                    },
                                    "screamingSnakeCase": {
                                        "unsafeName": "SOME_ENUM",
                                        "safeName": "SOME_ENUM"
                                    },
                                    "pascalCase": {
                                        "unsafeName": "SomeEnum",
                                        "safeName": "SomeEnum"
                                    }
                                },
                                "wireValue": "some-enum"
                            },
                            "valueType": {
                                "_type": "container",
                                "container": {
                                    "_type": "optional",
                                    "optional": {
                                        "_type": "named",
                                        "name": {
                                            "originalName": "myEnum",
                                            "camelCase": {
                                                "unsafeName": "myEnum",
                                                "safeName": "myEnum"
                                            },
                                            "snakeCase": {
                                                "unsafeName": "my_enum",
                                                "safeName": "my_enum"
                                            },
                                            "screamingSnakeCase": {
                                                "unsafeName": "MY_ENUM",
                                                "safeName": "MY_ENUM"
                                            },
                                            "pascalCase": {
                                                "unsafeName": "MyEnum",
                                                "safeName": "MyEnum"
                                            }
                                        },
                                        "fernFilepath": {
                                            "allParts": [
                                                {
                                                    "originalName": "svc",
                                                    "camelCase": {
                                                        "unsafeName": "svc",
                                                        "safeName": "svc"
                                                    },
                                                    "snakeCase": {
                                                        "unsafeName": "svc",
                                                        "safeName": "svc"
                                                    },
                                                    "screamingSnakeCase": {
                                                        "unsafeName": "SVC",
                                                        "safeName": "SVC"
                                                    },
                                                    "pascalCase": {
                                                        "unsafeName": "Svc",
                                                        "safeName": "Svc"
                                                    }
                                                }
                                            ],
                                            "packagePath": [],
                                            "file": {
                                                "originalName": "svc",
                                                "camelCase": {
                                                    "unsafeName": "svc",
                                                    "safeName": "svc"
                                                },
                                                "snakeCase": {
                                                    "unsafeName": "svc",
                                                    "safeName": "svc"
                                                },
                                                "screamingSnakeCase": {
                                                    "unsafeName": "SVC",
                                                    "safeName": "SVC"
                                                },
                                                "pascalCase": {
                                                    "unsafeName": "Svc",
                                                    "safeName": "Svc"
                                                }
                                            }
                                        },
                                        "typeId": "type_svc:myEnum"
                                    }
                                }
                            },
                            "allowMultiple": true,
                            "availability": null,
                            "docs": null
                        }
                    ],
                    "headers": [],
                    "requestBody": null,
                    "sdkRequest": {
                        "shape": {
                            "type": "wrapper",
                            "wrapperName": {
                                "originalName": "TEST",
                                "camelCase": {
                                    "unsafeName": "test",
                                    "safeName": "test"
                                },
                                "snakeCase": {
                                    "unsafeName": "test",
                                    "safeName": "test"
                                },
                                "screamingSnakeCase": {
                                    "unsafeName": "TEST",
                                    "safeName": "TEST"
                                },
                                "pascalCase": {
                                    "unsafeName": "Test",
                                    "safeName": "Test"
                                }
                            },
                            "bodyKey": {
                                "originalName": "body",
                                "camelCase": {
                                    "unsafeName": "body",
                                    "safeName": "body"
                                },
                                "snakeCase": {
                                    "unsafeName": "body",
                                    "safeName": "body"
                                },
                                "screamingSnakeCase": {
                                    "unsafeName": "BODY",
                                    "safeName": "BODY"
                                },
                                "pascalCase": {
                                    "unsafeName": "Body",
                                    "safeName": "Body"
                                }
                            }
                        },
                        "requestParameterName": {
                            "originalName": "request",
                            "camelCase": {
                                "unsafeName": "request",
                                "safeName": "request"
                            },
                            "snakeCase": {
                                "unsafeName": "request",
                                "safeName": "request"
                            },
                            "screamingSnakeCase": {
                                "unsafeName": "REQUEST",
                                "safeName": "REQUEST"
                            },
                            "pascalCase": {
                                "unsafeName": "Request",
                                "safeName": "Request"
                            }
                        }
                    },
                    "response": {
                        "body": {
                            "type": "json",
                            "value": {
                                "type": "response",
                                "responseBodyType": {
                                    "_type": "primitive",
                                    "primitive": "STRING"
                                },
                                "docs": null
                            }
                        },
                        "status-code": null
                    },
                    "errors": [],
                    "examples": [
                        {
                            "exampleType": "generated",
                            "url": "/test",
                            "rootPathParameters": [],
                            "servicePathParameters": [],
                            "endpointPathParameters": [],
                            "serviceHeaders": [],
                            "endpointHeaders": [],
                            "queryParameters": [
                                {
                                    "name": {
                                        "name": {
                                            "originalName": "some-enum",
                                            "camelCase": {
                                                "unsafeName": "someEnum",
                                                "safeName": "someEnum"
                                            },
                                            "snakeCase": {
                                                "unsafeName": "some_enum",
                                                "safeName": "some_enum"
                                            },
                                            "screamingSnakeCase": {
                                                "unsafeName": "SOME_ENUM",
                                                "safeName": "SOME_ENUM"
                                            },
                                            "pascalCase": {
                                                "unsafeName": "SomeEnum",
                                                "safeName": "SomeEnum"
                                            }
                                        },
                                        "wireValue": "some-enum"
                                    },
                                    "value": {
                                        "shape": {
                                            "type": "named",
                                            "typeName": {
                                                "name": {
                                                    "originalName": "myEnum",
                                                    "camelCase": {
                                                        "unsafeName": "myEnum",
                                                        "safeName": "myEnum"
                                                    },
                                                    "snakeCase": {
                                                        "unsafeName": "my_enum",
                                                        "safeName": "my_enum"
                                                    },
                                                    "screamingSnakeCase": {
                                                        "unsafeName": "MY_ENUM",
                                                        "safeName": "MY_ENUM"
                                                    },
                                                    "pascalCase": {
                                                        "unsafeName": "MyEnum",
                                                        "safeName": "MyEnum"
                                                    }
                                                },
                                                "fernFilepath": {
                                                    "allParts": [
                                                        {
                                                            "originalName": "svc",
                                                            "camelCase": {
                                                                "unsafeName": "svc",
                                                                "safeName": "svc"
                                                            },
                                                            "snakeCase": {
                                                                "unsafeName": "svc",
                                                                "safeName": "svc"
                                                            },
                                                            "screamingSnakeCase": {
                                                                "unsafeName": "SVC",
                                                                "safeName": "SVC"
                                                            },
                                                            "pascalCase": {
                                                                "unsafeName": "Svc",
                                                                "safeName": "Svc"
                                                            }
                                                        }
                                                    ],
                                                    "packagePath": [],
                                                    "file": {
                                                        "originalName": "svc",
                                                        "camelCase": {
                                                            "unsafeName": "svc",
                                                            "safeName": "svc"
                                                        },
                                                        "snakeCase": {
                                                            "unsafeName": "svc",
                                                            "safeName": "svc"
                                                        },
                                                        "screamingSnakeCase": {
                                                            "unsafeName": "SVC",
                                                            "safeName": "SVC"
                                                        },
                                                        "pascalCase": {
                                                            "unsafeName": "Svc",
                                                            "safeName": "Svc"
                                                        }
                                                    }
                                                },
                                                "typeId": "type_svc:myEnum"
                                            },
                                            "shape": {
                                                "type": "enum",
                                                "value": {
                                                    "name": {
                                                        "originalName": "one",
                                                        "camelCase": {
                                                            "unsafeName": "one",
                                                            "safeName": "one"
                                                        },
                                                        "snakeCase": {
                                                            "unsafeName": "one",
                                                            "safeName": "one"
                                                        },
                                                        "screamingSnakeCase": {
                                                            "unsafeName": "ONE",
                                                            "safeName": "ONE"
                                                        },
                                                        "pascalCase": {
                                                            "unsafeName": "One",
                                                            "safeName": "One"
                                                        }
                                                    },
                                                    "wireValue": "one"
                                                }
                                            }
                                        },
                                        "jsonExample": "one"
                                    }
                                }
                            ],
                            "request": null,
                            "name": null,
                            "codeSamples": null,
                            "response": {
                                "type": "ok"
                            },
                            "docs": null
                        }
                    ],
                    "pagination": null,
                    "availability": null,
                    "docs": null
                }
            ]
        }
    },
    "constants": {
        "errorInstanceIdKey": {
            "name": {
                "originalName": "errorInstanceId",
                "camelCase": {
                    "unsafeName": "errorInstanceId",
                    "safeName": "errorInstanceId"
                },
                "snakeCase": {
                    "unsafeName": "error_instance_id",
                    "safeName": "error_instance_id"
                },
                "screamingSnakeCase": {
                    "unsafeName": "ERROR_INSTANCE_ID",
                    "safeName": "ERROR_INSTANCE_ID"
                },
                "pascalCase": {
                    "unsafeName": "ErrorInstanceId",
                    "safeName": "ErrorInstanceId"
                }
            },
            "wireValue": "errorInstanceId"
        }
    },
    "environments": null,
    "errorDiscriminationStrategy": {
        "type": "statusCode"
    },
    "basePath": null,
    "pathParameters": [],
    "variables": [],
    "serviceTypeReferenceInfo": {
        "typesReferencedOnlyByService": {
            "service_svc": [
                "type_svc:myEnum"
            ]
        },
        "sharedTypes": []
    },
    "webhookGroups": {},
    "websocketChannels": {},
    "subpackages": {
        "subpackage_svc": {
            "name": {
                "originalName": "svc",
                "camelCase": {
                    "unsafeName": "svc",
                    "safeName": "svc"
                },
                "snakeCase": {
                    "unsafeName": "svc",
                    "safeName": "svc"
                },
                "screamingSnakeCase": {
                    "unsafeName": "SVC",
                    "safeName": "SVC"
                },
                "pascalCase": {
                    "unsafeName": "Svc",
                    "safeName": "Svc"
                }
            },
            "fernFilepath": {
                "allParts": [
                    {
                        "originalName": "svc",
                        "camelCase": {
                            "unsafeName": "svc",
                            "safeName": "svc"
                        },
                        "snakeCase": {
                            "unsafeName": "svc",
                            "safeName": "svc"
                        },
                        "screamingSnakeCase": {
                            "unsafeName": "SVC",
                            "safeName": "SVC"
                        },
                        "pascalCase": {
                            "unsafeName": "Svc",
                            "safeName": "Svc"
                        }
                    }
                ],
                "packagePath": [],
                "file": {
                    "originalName": "svc",
                    "camelCase": {
                        "unsafeName": "svc",
                        "safeName": "svc"
                    },
                    "snakeCase": {
                        "unsafeName": "svc",
                        "safeName": "svc"
                    },
                    "screamingSnakeCase": {
                        "unsafeName": "SVC",
                        "safeName": "SVC"
                    },
                    "pascalCase": {
                        "unsafeName": "Svc",
                        "safeName": "Svc"
                    }
                }
            },
            "service": "service_svc",
            "types": [
                "type_svc:myEnum"
            ],
            "errors": [],
            "subpackages": [],
            "navigationConfig": null,
            "webhooks": null,
            "websocket": null,
            "hasEndpointsInTree": true,
            "docs": null
        }
    },
    "rootPackage": {
        "fernFilepath": {
            "allParts": [],
            "packagePath": [],
            "file": null
        },
        "websocket": null,
        "service": null,
        "types": [],
        "errors": [],
        "subpackages": [
            "subpackage_svc"
        ],
        "webhooks": null,
        "navigationConfig": null,
        "hasEndpointsInTree": true,
        "docs": null
    },
    "sdkConfig": {
        "isAuthMandatory": false,
        "hasStreamingEndpoints": false,
        "hasFileDownloadEndpoints": false,
        "platformHeaders": {
            "language": "X-Fern-Language",
            "sdkName": "X-Fern-SDK-Name",
            "sdkVersion": "X-Fern-SDK-Version"
        }
    }
}