{
  "totalTestTimeSeconds": 3477,
  "groups": [
    {
      "fixtures": [
        "version-no-default",
        "multiple-request-bodies",
        "nullable-optional",
        "client-side-params",
        "any-auth",
        "pagination",
        "trace",
        "inferred-auth-explicit",
        "oauth-client-credentials-nested-root",
        "server-sent-event-examples",
        "variables",
        "custom-auth",
        "errors",
        "oauth-client-credentials-default",
        "streaming:.",
        "multi-url-environment",
        "public-object"
      ],
      "groupTotalTimeSeconds": 346
    },
    {
      "fixtures": ["accept-header", "file-download", "error-property", "audiences", "folders"],
      "groupTotalTimeSeconds": 349
    },
    {
      "fixtures": ["alias", "file-upload", "extra-properties", "cross-package-type-names", "go-content-type"],
      "groupTotalTimeSeconds": 349
    },
    {
      "fixtures": [
        "api-wide-base-path",
        "http-head",
        "oauth-client-credentials-custom",
        "server-sent-events",
        "inferred-auth-implicit-no-expiry",
        "path-parameters",
        "reserved-keywords"
      ],
      "groupTotalTimeSeconds": 349
    },
    {
      "fixtures": [
        "query-parameters-openapi",
        "exhaustive",
        "multi-url-environment-no-default",
        "response-property",
        "imdb",
        "mixed-file-directory",
        "license"
      ],
      "groupTotalTimeSeconds": 348
    },
    {
      "fixtures": [
        "query-parameters-openapi-as-objects",
        "alias-extends",
        "no-environment",
        "optional",
        "mixed-case",
        "plain-text",
        "undiscriminated-unions",
        "inferred-auth-implicit",
        "property-access",
        "simple-api",
        "websocket",
        "empty-clients",
        "go-bytes-request",
        "oauth-client-credentials-environment-variables",
        "unknown",
        "oauth-client-credentials-with-variables",
        "enum",
        "request-parameters"
      ],
      "groupTotalTimeSeconds": 348
    },
    {
      "fixtures": [
        "version",
        "simple-fhir",
        "literals-unions",
        "query-parameters",
        "nullable",
        "single-url-environment-default",
        "basic-auth-environment-variables",
        "circular-references-advanced",
        "oauth-client-credentials",
        "required-nullable",
        "streaming-parameter",
        "websocket-bearer-auth",
        "multi-line-docs",
        "objects-with-imports",
        "validation",
        "package-yml",
        "examples"
      ],
      "groupTotalTimeSeconds": 345
    },
    {
      "fixtures": [
        "auth-environment-variables",
        "bytes-upload",
        "websocket-inferred-auth",
        "pagination-custom",
        "literal"
      ],
      "groupTotalTimeSeconds": 348
    },
    {
      "fixtures": [
        "bearer-token-environment-variable",
        "content-type",
        "basic-auth",
        "single-url-environment-no-default",
        "object"
      ],
      "groupTotalTimeSeconds": 348
    },
    {
      "fixtures": ["bytes-download", "extends", "circular-references", "unions", "idempotency-headers:."],
      "groupTotalTimeSeconds": 347
    }
  ]
}
