{
  "totalTestTimeSeconds": 1221,
  "groups": [
    {
      "fixtures": [
        "version",
        "circular-references-advanced",
        "examples",
        "nullable-optional",
        "websocket",
        "empty-clients",
        "inferred-auth-explicit",
        "multi-line-docs",
        "oauth-client-credentials",
        "pagination-custom",
        "public-object",
        "custom-auth",
        "no-environment",
        "server-sent-events"
      ],
      "groupTotalTimeSeconds": 121
    },
    {
      "fixtures": ["accept-header", "bytes-upload", "basic-auth", "license", "optional", "unknown"],
      "groupTotalTimeSeconds": 123
    },
    {
      "fixtures": ["alias", "content-type", "circular-references", "literals-unions", "package-yml", "variables"],
      "groupTotalTimeSeconds": 123
    },
    {
      "fixtures": ["alias-extends", "extends", "cross-package-type-names", "mixed-case", "request-parameters", "imdb"],
      "groupTotalTimeSeconds": 122
    },
    {
      "fixtures": [
        "api-wide-base-path",
        "file-download",
        "validation",
        "mixed-file-directory",
        "reserved-keywords",
        "required-nullable"
      ],
      "groupTotalTimeSeconds": 122
    },
    {
      "fixtures": [
        "auth-environment-variables",
        "file-upload",
        "websocket-inferred-auth",
        "multi-url-environment",
        "server-sent-event-examples",
        "ruby-reserved-word-properties"
      ],
      "groupTotalTimeSeconds": 122
    },
    {
      "fixtures": [
        "query-parameters-openapi",
        "client-side-params",
        "exhaustive:extra-deps",
        "simple-fhir",
        "audiences",
        "errors",
        "inferred-auth-implicit",
        "multi-url-environment-no-default",
        "oauth-client-credentials-default",
        "path-parameters",
        "query-parameters",
        "enum",
        "oauth-client-credentials-custom",
        "simple-api"
      ],
      "groupTotalTimeSeconds": 122
    },
    {
      "fixtures": [
        "query-parameters-openapi-as-objects",
        "pagination",
        "exhaustive:flattened-module-structure",
        "unions",
        "basic-auth-environment-variables",
        "folders",
        "inferred-auth-implicit-no-expiry",
        "multiple-request-bodies",
        "object",
        "plain-text",
        "single-url-environment-no-default",
        "error-property",
        "oauth-client-credentials-environment-variables",
        "single-url-environment-default"
      ],
      "groupTotalTimeSeconds": 122
    },
    {
      "fixtures": [
        "version-no-default",
        "trace",
        "exhaustive:no-custom-config",
        "response-property",
        "websocket-bearer-auth",
        "idempotency-headers",
        "literal",
        "nullable",
        "objects-with-imports",
        "property-access",
        "undiscriminated-unions",
        "extra-properties",
        "oauth-client-credentials-nested-root",
        "streaming"
      ],
      "groupTotalTimeSeconds": 122
    },
    {
      "fixtures": [
        "bearer-token-environment-variable",
        "bytes-download",
        "any-auth",
        "http-head",
        "oauth-client-credentials-with-variables",
        "streaming-parameter"
      ],
      "groupTotalTimeSeconds": 122
    }
  ]
}
